<?xml version="1.0" encoding="UTF-8"?>
<entry>
	<name>Unknown</name>
	<source>
		<title>Source unknown</title>
		<subtitle>This grammar looks like it was copy-pasted from a PDF</subtitle>
		<date>15 June 2012</date>
	</source>
	<readme/>
	<grammar>
		<dir>fetched</dir>
		<level>0</level>
		<method>copy</method>
	</grammar>
	<grammar>
		<of>Clafer</of>
		<dir>extracted</dir>
		<level>1</level>
		<method>semi-automatic</method>
		<derivedFrom>fetched</derivedFrom>
		<!--  -->
		<toolused>hunter</toolused>
		<fileused>clafer.edd</fileused>
		<toolused>xbgf</toolused>
		<fileused>post-extract.xbgf</fileused>
	</grammar>
	<grammar>
		<of>Clafer</of>
		<dir>connected</dir>
		<level>1</level>
		<method>semi-automatic</method>
		<derivedFrom>extracted</derivedFrom>
		<!--  -->
		<toolused>exbgf</toolused>
		<fileused>deyaccify.exbgf</fileused>
		<fileused>beautify.exbgf</fileused>
	</grammar>
</entry>
