<?xml version="1.0" encoding="UTF-8"?>
<entry>
	<name>SAD</name>
	<long>Software Architecture Descriptions</long>
	<source>
		<author>Julien Baudry</author>
		<file>Architectural_Description.ecore</file>
		<date>2006/07/20</date>
	</source>
	<source>
		<author>Mohamed Mancona Kandé, Alfred Strohmeier</author>
		<title>Towards a UML Profile for Software Architecture Descriptions</title>
		<subtitle>LNCS 1939</subtitle>
		<date>2000</date>
	</source>
	<link>
		<uri>http://www.emn.fr/z-info/atlanmod/index.php/Ecore</uri>
		<name>Atlantic</name>
	</link>
	<readme/>
	<grammar>
		<dir>fetched</dir>
		<level>0</level>
		<method>download</method>
		<format>XMI</format>
	</grammar>
	<grammar>
		<of>Software Architecture Descriptions</of>
		<dir>extracted</dir>
		<level>1</level>
		<derivedFrom>fetched</derivedFrom>
		<method>automatic</method>
		<toolused>ecore2bgf</toolused>
	</grammar>
</entry>
