<?xml version="1.0" encoding="UTF-8"?>
<entry>
	<name>ISO N2723</name>
	<source>
		<standard>ISO/IEC SC22/WG21 N2723=08-0233 Working Draft</standard>
		<title>Standard for Programming Language C++</title>
		<date>August 2008</date>
		<specific>Annex A, pages 1089–1101</specific>
	</source>
	<readme/>
	<grammar>
		<dir>fetched</dir>
		<level>0</level>
		<method>copy</method>
	</grammar>
	<grammar>
		<dir>extracted</dir>
		<level>1</level>
		<method>automatic</method>
		<toolused>pdf2lll</toolused>
		<toolused>lll2bgf</toolused>
		<fileused>post-extract.xbgf</fileused>
		<toolused>xbgf</toolused>
		<toolused>subgrammar</toolused>
	</grammar>
</entry>
