<?xml version="1.0" encoding="UTF-8"?>
<entry>
	<name>Schema</name>
	<source>
		<author>Hugo Brunelière</author>
		<title>RelationalDBSchema 1.0</title>
		<file>RelationalDBSchema.ecore</file>
		<date>2006/10/31</date>
	</source>
	<readme/>
	<link>
		<uri>http://www.emn.fr/z-info/atlanmod/index.php/Ecore</uri>
		<name>Atlantic</name>
	</link>
	<grammar>
		<dir>fetched</dir>
		<level>0</level>
		<method>download</method>
		<format>XMI</format>
	</grammar>
	<grammar>
		<of>Relational Database Schema</of>
		<dir>extracted</dir>
		<level>1</level>
		<method>automatic</method>
		<derivedFrom>fetched</derivedFrom>
		<!--  -->
		<toolused>ecore2bgf</toolused>
	</grammar>
</entry>
