<?xml version="1.0" encoding="UTF-8"?>
<entry>
	<name>Abstract</name>
	<source>
		<author>Tijs van der Storm</author>
		<file>lang::csv::ast::CSV</file>
		<date>18 March 2012</date>
		<link>
			<uri>https://github.com/cwi-swat/rascal/blob/master/src/org/rascalmpl/library/lang/csv/ast/CSV.rsc</uri>
			<name>GitHub</name>
		</link>
	</source>
	<readme/>
	<grammar>
		<dir>fetched</dir>
		<level>0</level>
		<method>git</method>
	</grammar>
	<grammar>
		<of>Comma-Separated Values (CSV)</of>
		<dir>extracted</dir>
		<level>1</level>
		<method>automatic</method>
		<derivedFrom>fetched</derivedFrom>
		<!--  -->
		<toolused>rscd2bgf</toolused>
		<fileused>connect.glue</fileused>
		<toolused>grammarlab</toolused>
	</grammar>
	<grammar>
		<of>Comma-Separated Values (CSV)</of>
		<dir>connected</dir>
		<level>2</level>
		<method>semi-automated</method>
		<derivedFrom>extracted</derivedFrom>
		<!--  -->
		<fileused>connect.glue</fileused>
		<toolused>grammarlab</toolused>
	</grammar>
</entry>
