<?xml version="1.0" encoding="UTF-8"?>
<entry>
	<name>ISO/IEC 9899:TC3</name>
	<source>
		<standard>ISO/IEC 9899:TC3</standard>
		<title>WG14/N1256 Committee Draft</title>
		<date>September 2007</date>
		<specific>Annex A, pages 403–418</specific>
	</source>
	<readme/>
	<grammar>
		<dir>fetched</dir>
		<level>0</level>
		<method>copy</method>
	</grammar>
	<grammar>
		<of>C99</of>
		<dir>extracted</dir>
		<level>1</level>
		<method>automatic</method>
		<derivedFrom>fetched</derivedFrom>
		<!--  -->
		<toolused>pdf2lll</toolused>
		<toolused>lll2bgf</toolused>
		<toolused>normalise</toolused>
		<fileused>correct.xbgf</fileused>
		<toolused>xbgf</toolused>
		<toolused>subgrammar</toolused>
	</grammar>
</entry>
