<?xml version="1.0" encoding="UTF-8"?>
<entry>
	<name>SDF</name>
	<source>
		<author>Jurgen Vinju</author>
		<author>Bas Basten</author>
		<file>aterm/syntax/*.sdf</file>
		<date>February 2006 – January 2009</date>
	</source>
	<!-- <readme/> -->
	<link>
		<uri>http://www.meta-environment.org/</uri>
		<name>MetaEnv</name>
	</link>
	<grammar>
		<dir>fetched</dir>
		<level>0</level>
		<method>git</method>
		<format>SDF</format>
	</grammar>
	<grammar>
		<of>ATerms</of>
		<dir>extracted</dir>
		<level>1</level>
		<method>automatic</method>
		<derivedFrom>fetched</derivedFrom>
		<!--  -->
		<toolused>sdf2bgf</toolused>
	</grammar>
</entry>
