<?xml version="1.0" encoding="UTF-8"?>
<entry>
	<name>ZakonGroup OpenConf</name>
	<source>
		<author>OntoFarm Project</author>
		<file>OpenConf.owl.ecore</file>
		<date>June 2009</date>
	</source>
	<link>
		<uri>http://www.zakongroup.com/technology/openconf.shtml</uri>
		<name>ZakonGroup</name>
	</link>
	<readme/>
	<link>
		<uri>http://www.emn.fr/z-info/atlanmod/index.php/Ecore</uri>
		<name>Atlantic</name>
	</link>
	<grammar>
		<dir>fetched</dir>
		<level>0</level>
		<method>download</method>
	</grammar>
	<grammar>
		<of>ZakonGroup OpenConf</of>
		<dir>extracted</dir>
		<level>1</level>
		<method>automatic</method>
		<derivedFrom>fetched</derivedFrom>
		<!--  -->
		<toolused>ecore2bgf</toolused>
	</grammar>
</entry>
